dmtipy/__init__.py
dmtipy/create_table_from_csv.py
dmtipy-0.0.5.dist-info/METADATA
dmtipy-0.0.5.dist-info/WHEEL
dmtipy-0.0.5.dist-info/top_level.txt
dmtipy-0.0.5.dist-info/RECORD
