Metadata-Version: 2.1
Name: dmtipy
Version: 0.0.5
Summary: DMTI Python Library to optimize every data processing in PNM
Home-page: https://github.com/dwieka21-bit
Author: Dwieka
Author-email: patriadwieka@gmail.com
License: MIT
Classifier: Intended Audience :: Developers
Classifier: License :: OSI Approved :: MIT License
Classifier: Programming Language :: Python
Classifier: Programming Language :: Python :: 3
Classifier: Programming Language :: Python :: 3.6
Classifier: Programming Language :: Python :: 3.7
Classifier: Programming Language :: Python :: 3.8
Classifier: Programming Language :: Python :: 3.9
Classifier: Programming Language :: Python :: 3.10
Classifier: Programming Language :: Python :: 3.11
Classifier: Operating System :: OS Independent
Requires-Dist: pandas
Requires-Dist: pymssql
